{
  "notes": [
    {
      "content": "custom-hooks are awesome!",
      "id": 1
    },
    {
      "content": "best feature ever <3",
      "id": 2
    },
    {
      "content": "houi",
      "id": 3
    },
    {
      "content": "hui",
      "id": 4
    },
    {
      "content": "hui",
      "id": 5
    },
    {
      "content": "h98",
      "id": 6
    },
    {
      "content": "seis",
      "id": 7
    },
    {
      "content": "??",
      "id": 8
    },
    {
      "content": "ajid",
      "id": 9
    },
    {
      "content": "heu",
      "id": 10
    },
    {
      "content": "wuj",
      "id": 11
    },
    {
      "content": "wij",
      "id": 12
    },
    {
      "content": "pah",
      "id": 13
    },
    {
      "content": "juhuu",
      "id": 14
    },
    {
      "content": "wuhuuu",
      "id": 15
    },
    {
      "content": "wuhuuu",
      "id": 16
    },
    {
      "content": "noni",
      "id": 17
    },
    {
      "content": "perse",
      "id": 18
    }
  ],
  "persons": [
    {
      "name": "mluukkai",
      "number": "040-5483923",
      "id": 1
    },
    {
      "name": "hojo",
      "number": "3",
      "id": 2
    },
    {
      "name": "hojo",
      "number": "3",
      "id": 3
    },
    {
      "name": "hojo",
      "number": "3",
      "id": 4
    },
    {
      "name": "joska",
      "number": "18351",
      "id": 5
    },
    {
      "name": "joska",
      "number": "13414",
      "id": 6
    },
    {
      "name": "joska",
      "number": "13414",
      "id": 7
    },
    {
      "name": "joska",
      "number": "135135",
      "id": 8
    }
  ]
}